{
  "name": "random_sc_n5_m8_seed79",
  "family": "random_sc",
  "seed": 79,
  "n_nodes": 5,
  "edges": [
    [
      0,
      1
    ],
    [
      1,
      2
    ],
    [
      2,
      3
    ],
    [
      3,
      4
    ],
    [
      4,
      0
    ],
    [
      0,
      4
    ],
    [
      2,
      1
    ],
    [
      1,
      4
    ]
  ],
  "metrics": {
    "n_nodes": 5,
    "n_edges": 8,
    "p": 8,
    "strongly_connected": true,
    "edges": [
      [
        0,
        1
      ],
      [
        1,
        2
      ],
      [
        2,
        3
      ],
      [
        3,
        4
      ],
      [
        4,
        0
      ],
      [
        0,
        4
      ],
      [
        2,
        1
      ],
      [
        1,
        4
      ]
    ],
    "tree_counts_enum": [
      3,
      2,
      1,
      1,
      6
    ],
    "tree_counts_det": [
      3,
      2,
      1,
      1,
      6
    ],
    "tree_counts_match_det": true,
    "tree_enumeration_truncated": false,
    "max_trees_per_root": null,
    "n_trees_total_enum": 13,
    "rank_M": 8,
    "rank_D": 7,
    "rank_D_anchor": 7,
    "d_rel": 56,
    "effective_rank_D": 4.904240161269271,
    "condition_number_D": 4.2664003793068535,
    "effective_rank_D_masked": 39.23392129015419,
    "condition_number_D_masked": 4.2664003793068535,
    "singular_values_D_masked": [
      2.864073179688171,
      2.381145090877389,
      1.7320508075688774,
      1.66584128691041,
      0.957479099391611,
      0.9115577140376832,
      0.6713090486255503,
      3.6392962131356345e-16,
      2.864073179688171,
      2.381145090877389,
      1.7320508075688774,
      1.66584128691041,
      0.957479099391611,
      0.9115577140376832,
      0.6713090486255503,
      3.6392962131356345e-16,
      2.864073179688171,
      2.381145090877389,
      1.7320508075688774,
      1.66584128691041,
      0.957479099391611,
      0.9115577140376832,
      0.6713090486255503,
      3.6392962131356345e-16,
      2.864073179688171,
      2.381145090877389,
      1.7320508075688774,
      1.66584128691041,
      0.957479099391611,
      0.9115577140376832,
      0.6713090486255503,
      3.6392962131356345e-16,
      2.864073179688171,
      2.381145090877389,
      1.7320508075688774,
      1.66584128691041,
      0.957479099391611,
      0.9115577140376832,
      0.6713090486255503,
      3.6392962131356345e-16,
      2.864073179688171,
      2.381145090877389,
      1.7320508075688774,
      1.66584128691041,
      0.957479099391611,
      0.9115577140376832,
      0.6713090486255503,
      3.6392962131356345e-16,
      2.864073179688171,
      2.381145090877389,
      1.7320508075688774,
      1.66584128691041,
      0.957479099391611,
      0.9115577140376832,
      0.6713090486255503,
      3.6392962131356345e-16,
      2.864073179688171,
      2.381145090877389,
      1.7320508075688774,
      1.66584128691041,
      0.957479099391611,
      0.9115577140376832,
      0.6713090486255503,
      3.6392962131356345e-16
    ],
    "singular_values_D": [
      2.864073179688171,
      2.381145090877389,
      1.7320508075688774,
      1.66584128691041,
      0.957479099391611,
      0.9115577140376832,
      0.6713090486255503,
      3.6392962131356345e-16
    ],
    "singular_values_D_anchor": [
      4.8983090962473295,
      2.4510463803853386,
      2.171442481174453,
      1.6685672137552883,
      1.0314190948902995,
      0.9561187405907432,
      0.7222688194427993,
      2.3812017047259053e-16
    ],
    "root_tree_count_cv": 0.7133552688842849,
    "root_tree_count_gini": 0.36923076923076925,
    "edge_participation": [
      0.5384615384615384,
      0.38461538461538464,
      0.6153846153846154,
      0.9230769230769231,
      0.5384615384615384,
      0.23076923076923078,
      0.3076923076923077,
      0.46153846153846156
    ],
    "edge_participation_mean": 0.5,
    "edge_participation_var": 0.039940828402366874,
    "edge_participation_gini": 0.21634615384615397,
    "bottleneck_edge_fraction_095": 0.0,
    "mean_shortest_path": 2.0,
    "comparison_branch_d_rel_values": [
      14,
      14,
      14
    ],
    "comparison_branch_d_rel_min": 14,
    "comparison_branch_d_rel_mean": 14.0,
    "comparison_branch_d_rel_max": 14,
    "comparison_branch_d_rel_gini": 0.0,
    "comparison_branch_common_d_rel_values": [
      14,
      14,
      14
    ],
    "comparison_branch_common_d_rel_min": 14,
    "comparison_branch_common_d_rel_mean": 14.0,
    "comparison_branch_common_d_rel_max": 14,
    "comparison_branch_common_d_rel_gini": 0.0,
    "comparison_branch_input_count_values": [
      16,
      16,
      16
    ],
    "comparison_branch_input_count_min": 16,
    "comparison_branch_input_count_mean": 16.0,
    "comparison_branch_input_count_max": 16,
    "comparison_branch_input_count_gini": 0.0,
    "comparison_branch_input_overlap_values": [
      16,
      16,
      16
    ],
    "comparison_branch_input_overlap_min": 16,
    "comparison_branch_input_overlap_mean": 16.0,
    "comparison_branch_input_overlap_max": 16,
    "comparison_branch_input_overlap_gini": 0.0,
    "in_degree": [
      1,
      2,
      1,
      1,
      3
    ],
    "out_degree": [
      2,
      2,
      2,
      1,
      1
    ],
    "in_degree_cv": 0.5,
    "out_degree_cv": 0.30618621784789724
  }
}