{
  "run_dir": "/home/aadarwal/repos/topology/ICL/results/expanded_hard_sweeps/n5_m8_N3_D2/g0000_cycle_chords_seed1_trainseed3",
  "topology_name": "cycle_chords_n5_m8_seed1",
  "n_samples": 500,
  "n_repeats": 5,
  "device": "cpu",
  "baseline": {
    "target_accuracy": 85.19999980926514,
    "target_logprob_margin_mean": 1.5770456790924072,
    "target_logprob_margin_min": -1.82827889919281,
    "branch_active_tree_mi": 0.4718960446361917,
    "branch_active_root_mi": 0.3734352631382388,
    "tree_entropy_mean": 2.3055167198181152,
    "root_entropy_mean": 0.780943751335144,
    "active_tree_matched_comparison_gap_mean": -0.4423654719290732,
    "posterior_matched_comparison_gap_mean": -0.2973235792348156
  },
  "interventions": [
    {
      "intervention": "context_block_shuffle",
      "seed": 0,
      "coordinate_permutation": [
        4,
        5,
        0,
        1,
        2,
        3,
        6,
        7
      ],
      "repeat": 0,
      "target_accuracy": 6.199999898672104,
      "target_logprob_margin_mean": -4.872005939483643,
      "target_logprob_margin_min": -13.586104393005371,
      "branch_active_tree_mi": 0.5144859077198412,
      "branch_active_root_mi": 0.4044798846267711,
      "tree_entropy_mean": 2.2121288776397705,
      "root_entropy_mean": 0.7982609868049622,
      "active_tree_matched_comparison_gap_mean": -0.4551627527219894,
      "posterior_matched_comparison_gap_mean": -0.29069004001942406,
      "target_accuracy_delta": -78.99999991059303,
      "target_logprob_margin_mean_delta": -6.44905161857605,
      "target_logprob_margin_min_delta": -11.757825493812561,
      "branch_active_tree_mi_delta": 0.042589863083649426,
      "branch_active_root_mi_delta": 0.031044621488532265,
      "tree_entropy_mean_delta": -0.09338784217834473,
      "root_entropy_mean_delta": 0.017317235469818115,
      "active_tree_matched_comparison_gap_mean_delta": -0.012797280792916199,
      "posterior_matched_comparison_gap_mean_delta": 0.0066335392153915596
    },
    {
      "intervention": "context_block_shuffle",
      "seed": 1,
      "coordinate_permutation": [
        4,
        5,
        0,
        1,
        2,
        3,
        6,
        7
      ],
      "repeat": 1,
      "target_accuracy": 6.199999898672104,
      "target_logprob_margin_mean": -4.872005939483643,
      "target_logprob_margin_min": -13.586104393005371,
      "branch_active_tree_mi": 0.5144859077198412,
      "branch_active_root_mi": 0.4044798846267711,
      "tree_entropy_mean": 2.2121288776397705,
      "root_entropy_mean": 0.7982609868049622,
      "active_tree_matched_comparison_gap_mean": -0.4551627527219894,
      "posterior_matched_comparison_gap_mean": -0.29069004001942406,
      "target_accuracy_delta": -78.99999991059303,
      "target_logprob_margin_mean_delta": -6.44905161857605,
      "target_logprob_margin_min_delta": -11.757825493812561,
      "branch_active_tree_mi_delta": 0.042589863083649426,
      "branch_active_root_mi_delta": 0.031044621488532265,
      "tree_entropy_mean_delta": -0.09338784217834473,
      "root_entropy_mean_delta": 0.017317235469818115,
      "active_tree_matched_comparison_gap_mean_delta": -0.012797280792916199,
      "posterior_matched_comparison_gap_mean_delta": 0.0066335392153915596
    },
    {
      "intervention": "context_block_shuffle",
      "seed": 2,
      "coordinate_permutation": [
        4,
        5,
        0,
        1,
        2,
        3,
        6,
        7
      ],
      "repeat": 2,
      "target_accuracy": 6.199999898672104,
      "target_logprob_margin_mean": -4.872005939483643,
      "target_logprob_margin_min": -13.586104393005371,
      "branch_active_tree_mi": 0.5144859077198412,
      "branch_active_root_mi": 0.4044798846267711,
      "tree_entropy_mean": 2.2121288776397705,
      "root_entropy_mean": 0.7982609868049622,
      "active_tree_matched_comparison_gap_mean": -0.4551627527219894,
      "posterior_matched_comparison_gap_mean": -0.29069004001942406,
      "target_accuracy_delta": -78.99999991059303,
      "target_logprob_margin_mean_delta": -6.44905161857605,
      "target_logprob_margin_min_delta": -11.757825493812561,
      "branch_active_tree_mi_delta": 0.042589863083649426,
      "branch_active_root_mi_delta": 0.031044621488532265,
      "tree_entropy_mean_delta": -0.09338784217834473,
      "root_entropy_mean_delta": 0.017317235469818115,
      "active_tree_matched_comparison_gap_mean_delta": -0.012797280792916199,
      "posterior_matched_comparison_gap_mean_delta": 0.0066335392153915596
    },
    {
      "intervention": "context_block_shuffle",
      "seed": 3,
      "coordinate_permutation": [
        4,
        5,
        2,
        3,
        0,
        1,
        6,
        7
      ],
      "repeat": 3,
      "target_accuracy": 34.40000116825104,
      "target_logprob_margin_mean": -2.6728765964508057,
      "target_logprob_margin_min": -13.568455696105957,
      "branch_active_tree_mi": 0.5148799817187091,
      "branch_active_root_mi": 0.39965005119481617,
      "tree_entropy_mean": 2.3198468685150146,
      "root_entropy_mean": 0.7794969081878662,
      "active_tree_matched_comparison_gap_mean": -0.4466692137660037,
      "posterior_matched_comparison_gap_mean": -0.29375055917630266,
      "target_accuracy_delta": -50.7999986410141,
      "target_logprob_margin_mean_delta": -4.249922275543213,
      "target_logprob_margin_min_delta": -11.740176796913147,
      "branch_active_tree_mi_delta": 0.042983937082517354,
      "branch_active_root_mi_delta": 0.026214788056577343,
      "tree_entropy_mean_delta": 0.014330148696899414,
      "root_entropy_mean_delta": -0.001446843147277832,
      "active_tree_matched_comparison_gap_mean_delta": -0.004303741836930497,
      "posterior_matched_comparison_gap_mean_delta": 0.0035730200585129546
    },
    {
      "intervention": "context_block_shuffle",
      "seed": 4,
      "coordinate_permutation": [
        4,
        5,
        0,
        1,
        2,
        3,
        6,
        7
      ],
      "repeat": 4,
      "target_accuracy": 6.199999898672104,
      "target_logprob_margin_mean": -4.872005939483643,
      "target_logprob_margin_min": -13.586104393005371,
      "branch_active_tree_mi": 0.5144859077198412,
      "branch_active_root_mi": 0.4044798846267711,
      "tree_entropy_mean": 2.2121288776397705,
      "root_entropy_mean": 0.7982609868049622,
      "active_tree_matched_comparison_gap_mean": -0.4551627527219894,
      "posterior_matched_comparison_gap_mean": -0.29069004001942406,
      "target_accuracy_delta": -78.99999991059303,
      "target_logprob_margin_mean_delta": -6.44905161857605,
      "target_logprob_margin_min_delta": -11.757825493812561,
      "branch_active_tree_mi_delta": 0.042589863083649426,
      "branch_active_root_mi_delta": 0.031044621488532265,
      "tree_entropy_mean_delta": -0.09338784217834473,
      "root_entropy_mean_delta": 0.017317235469818115,
      "active_tree_matched_comparison_gap_mean_delta": -0.012797280792916199,
      "posterior_matched_comparison_gap_mean_delta": 0.0066335392153915596
    },
    {
      "intervention": "edge_projection_permutation",
      "seed": 1009,
      "edge_permutation": [
        1,
        0,
        2,
        7,
        6,
        5,
        4,
        3
      ],
      "repeat": 0,
      "target_accuracy": 44.600000977516174,
      "target_logprob_margin_mean": -1.1281657218933105,
      "target_logprob_margin_min": -13.665514945983887,
      "branch_active_tree_mi": 0.2200558415022333,
      "branch_active_root_mi": 0.1751337017461709,
      "tree_entropy_mean": 1.9627350568771362,
      "root_entropy_mean": 0.7013111710548401,
      "active_tree_matched_comparison_gap_mean": -0.345276908718433,
      "posterior_matched_comparison_gap_mean": -0.2780557116925571,
      "target_accuracy_delta": -40.59999883174896,
      "target_logprob_margin_mean_delta": -2.7052114009857178,
      "target_logprob_margin_min_delta": -11.837236046791077,
      "branch_active_tree_mi_delta": -0.2518402031339584,
      "branch_active_root_mi_delta": -0.19830156139206792,
      "tree_entropy_mean_delta": -0.342781662940979,
      "root_entropy_mean_delta": -0.07963258028030396,
      "active_tree_matched_comparison_gap_mean_delta": 0.09708856321064024,
      "posterior_matched_comparison_gap_mean_delta": 0.01926786754225851
    },
    {
      "intervention": "edge_projection_permutation",
      "seed": 1010,
      "edge_permutation": [
        0,
        3,
        5,
        1,
        2,
        6,
        7,
        4
      ],
      "repeat": 1,
      "target_accuracy": 28.79999876022339,
      "target_logprob_margin_mean": -4.66689920425415,
      "target_logprob_margin_min": -13.815510749816895,
      "branch_active_tree_mi": 0.2843866144819954,
      "branch_active_root_mi": 0.14894318178485177,
      "tree_entropy_mean": 1.7995190620422363,
      "root_entropy_mean": 0.7325893044471741,
      "active_tree_matched_comparison_gap_mean": -0.3005890996930445,
      "posterior_matched_comparison_gap_mean": -0.24354787799576202,
      "target_accuracy_delta": -56.40000104904175,
      "target_logprob_margin_mean_delta": -6.243944883346558,
      "target_logprob_margin_min_delta": -11.987231850624084,
      "branch_active_tree_mi_delta": -0.1875094301541963,
      "branch_active_root_mi_delta": -0.22449208135338705,
      "tree_entropy_mean_delta": -0.5059976577758789,
      "root_entropy_mean_delta": -0.04835444688796997,
      "active_tree_matched_comparison_gap_mean_delta": 0.14177637223602874,
      "posterior_matched_comparison_gap_mean_delta": 0.05377570123905359
    },
    {
      "intervention": "edge_projection_permutation",
      "seed": 1011,
      "edge_permutation": [
        5,
        4,
        3,
        6,
        7,
        0,
        1,
        2
      ],
      "repeat": 2,
      "target_accuracy": 36.399999260902405,
      "target_logprob_margin_mean": -2.665109634399414,
      "target_logprob_margin_min": -13.664383888244629,
      "branch_active_tree_mi": 0.3557137623261113,
      "branch_active_root_mi": 0.06366700165626192,
      "tree_entropy_mean": 1.725010871887207,
      "root_entropy_mean": 0.7793703675270081,
      "active_tree_matched_comparison_gap_mean": -0.3321997430193929,
      "posterior_matched_comparison_gap_mean": -0.24221921175977926,
      "target_accuracy_delta": -48.80000054836273,
      "target_logprob_margin_mean_delta": -4.242155313491821,
      "target_logprob_margin_min_delta": -11.836104989051819,
      "branch_active_tree_mi_delta": -0.11618228231008043,
      "branch_active_root_mi_delta": -0.3097682614819769,
      "tree_entropy_mean_delta": -0.5805058479309082,
      "root_entropy_mean_delta": -0.0015733838081359863,
      "active_tree_matched_comparison_gap_mean_delta": 0.1101657289096803,
      "posterior_matched_comparison_gap_mean_delta": 0.05510436747503636
    },
    {
      "intervention": "edge_projection_permutation",
      "seed": 1012,
      "edge_permutation": [
        2,
        5,
        4,
        7,
        3,
        6,
        1,
        0
      ],
      "repeat": 3,
      "target_accuracy": 37.20000088214874,
      "target_logprob_margin_mean": -4.0864481925964355,
      "target_logprob_margin_min": -13.701118469238281,
      "branch_active_tree_mi": 0.26878138358267606,
      "branch_active_root_mi": 0.0680934005681419,
      "tree_entropy_mean": 1.8065228462219238,
      "root_entropy_mean": 0.7075062990188599,
      "active_tree_matched_comparison_gap_mean": -0.2821441792163451,
      "posterior_matched_comparison_gap_mean": -0.19888676196476993,
      "target_accuracy_delta": -47.999998927116394,
      "target_logprob_margin_mean_delta": -5.663493871688843,
      "target_logprob_margin_min_delta": -11.872839570045471,
      "branch_active_tree_mi_delta": -0.20311466105351567,
      "branch_active_root_mi_delta": -0.30534186257009693,
      "tree_entropy_mean_delta": -0.4989938735961914,
      "root_entropy_mean_delta": -0.07343745231628418,
      "active_tree_matched_comparison_gap_mean_delta": 0.16022129271272811,
      "posterior_matched_comparison_gap_mean_delta": 0.09843681727004569
    },
    {
      "intervention": "edge_projection_permutation",
      "seed": 1013,
      "edge_permutation": [
        6,
        4,
        2,
        1,
        3,
        5,
        0,
        7
      ],
      "repeat": 4,
      "target_accuracy": 36.399999260902405,
      "target_logprob_margin_mean": -1.705532431602478,
      "target_logprob_margin_min": -13.781063079833984,
      "branch_active_tree_mi": 0.2868161795186734,
      "branch_active_root_mi": 0.1870975967255849,
      "tree_entropy_mean": 2.0340676307678223,
      "root_entropy_mean": 0.7982332706451416,
      "active_tree_matched_comparison_gap_mean": -0.32362455176070604,
      "posterior_matched_comparison_gap_mean": -0.23271261898735635,
      "target_accuracy_delta": -48.80000054836273,
      "target_logprob_margin_mean_delta": -3.2825781106948853,
      "target_logprob_margin_min_delta": -11.952784180641174,
      "branch_active_tree_mi_delta": -0.18507986511751834,
      "branch_active_root_mi_delta": -0.18633766641265392,
      "tree_entropy_mean_delta": -0.27144908905029297,
      "root_entropy_mean_delta": 0.01728951930999756,
      "active_tree_matched_comparison_gap_mean_delta": 0.11874092016836718,
      "posterior_matched_comparison_gap_mean_delta": 0.06461096024745927
    },
    {
      "intervention": "edge_rate_function_permutation",
      "seed": 2018,
      "edge_permutation": [
        2,
        6,
        5,
        0,
        7,
        3,
        1,
        4
      ],
      "repeat": 0,
      "target_accuracy": 28.79999876022339,
      "target_logprob_margin_mean": -3.9532899856567383,
      "target_logprob_margin_min": -13.815509796142578,
      "branch_active_tree_mi": 0.19197751923138723,
      "branch_active_root_mi": 0.07762462458259564,
      "tree_entropy_mean": 2.943500280380249,
      "root_entropy_mean": 0.48087912797927856,
      "active_tree_matched_comparison_gap_mean": -0.22604360502111887,
      "posterior_matched_comparison_gap_mean": -0.18174643748632616,
      "target_accuracy_delta": -56.40000104904175,
      "target_logprob_margin_mean_delta": -5.5303356647491455,
      "target_logprob_margin_min_delta": -11.987230896949768,
      "branch_active_tree_mi_delta": -0.2799185254048045,
      "branch_active_root_mi_delta": -0.29581063855564316,
      "tree_entropy_mean_delta": 0.6379835605621338,
      "root_entropy_mean_delta": -0.3000646233558655,
      "active_tree_matched_comparison_gap_mean_delta": 0.21632186690795435,
      "posterior_matched_comparison_gap_mean_delta": 0.11557714174848946
    },
    {
      "intervention": "edge_rate_function_permutation",
      "seed": 2019,
      "edge_permutation": [
        3,
        2,
        5,
        0,
        7,
        1,
        4,
        6
      ],
      "repeat": 1,
      "target_accuracy": 37.79999911785126,
      "target_logprob_margin_mean": -3.483433246612549,
      "target_logprob_margin_min": -13.815510749816895,
      "branch_active_tree_mi": 0.22637001037923457,
      "branch_active_root_mi": 0.060335239202862156,
      "tree_entropy_mean": 2.347294330596924,
      "root_entropy_mean": 0.5090771317481995,
      "active_tree_matched_comparison_gap_mean": -0.3168687089293227,
      "posterior_matched_comparison_gap_mean": -0.2147983325404742,
      "target_accuracy_delta": -47.40000069141388,
      "target_logprob_margin_mean_delta": -5.060478925704956,
      "target_logprob_margin_min_delta": -11.987231850624084,
      "branch_active_tree_mi_delta": -0.24552603425695715,
      "branch_active_root_mi_delta": -0.31310002393537667,
      "tree_entropy_mean_delta": 0.041777610778808594,
      "root_entropy_mean_delta": -0.2718666195869446,
      "active_tree_matched_comparison_gap_mean_delta": 0.12549676299975054,
      "posterior_matched_comparison_gap_mean_delta": 0.08252524669434141
    },
    {
      "intervention": "edge_rate_function_permutation",
      "seed": 2020,
      "edge_permutation": [
        0,
        2,
        1,
        3,
        4,
        7,
        5,
        6
      ],
      "repeat": 2,
      "target_accuracy": 27.799999713897705,
      "target_logprob_margin_mean": -4.723377704620361,
      "target_logprob_margin_min": -13.815510749816895,
      "branch_active_tree_mi": 0.30523620651772,
      "branch_active_root_mi": 0.1891070778733636,
      "tree_entropy_mean": 2.0567405223846436,
      "root_entropy_mean": 0.6379495859146118,
      "active_tree_matched_comparison_gap_mean": -0.42642207591520903,
      "posterior_matched_comparison_gap_mean": -0.337059107820675,
      "target_accuracy_delta": -57.40000009536743,
      "target_logprob_margin_mean_delta": -6.3004233837127686,
      "target_logprob_margin_min_delta": -11.987231850624084,
      "branch_active_tree_mi_delta": -0.16665983811847174,
      "branch_active_root_mi_delta": -0.18432818526487524,
      "tree_entropy_mean_delta": -0.24877619743347168,
      "root_entropy_mean_delta": -0.14299416542053223,
      "active_tree_matched_comparison_gap_mean_delta": 0.015943396013864186,
      "posterior_matched_comparison_gap_mean_delta": -0.03973552858585938
    },
    {
      "intervention": "edge_rate_function_permutation",
      "seed": 2021,
      "edge_permutation": [
        6,
        2,
        3,
        0,
        1,
        7,
        5,
        4
      ],
      "repeat": 3,
      "target_accuracy": 30.399999022483826,
      "target_logprob_margin_mean": -3.919482946395874,
      "target_logprob_margin_min": -13.815510749816895,
      "branch_active_tree_mi": 0.1940941500371934,
      "branch_active_root_mi": 0.0913201303666518,
      "tree_entropy_mean": 2.0280563831329346,
      "root_entropy_mean": 0.7044129371643066,
      "active_tree_matched_comparison_gap_mean": -0.31285698129096157,
      "posterior_matched_comparison_gap_mean": -0.24162356152012024,
      "target_accuracy_delta": -54.80000078678131,
      "target_logprob_margin_mean_delta": -5.496528625488281,
      "target_logprob_margin_min_delta": -11.987231850624084,
      "branch_active_tree_mi_delta": -0.2778018945989983,
      "branch_active_root_mi_delta": -0.282115132771587,
      "tree_entropy_mean_delta": -0.27746033668518066,
      "root_entropy_mean_delta": -0.0765308141708374,
      "active_tree_matched_comparison_gap_mean_delta": 0.12950849063811165,
      "posterior_matched_comparison_gap_mean_delta": 0.05570001771469538
    },
    {
      "intervention": "edge_rate_function_permutation",
      "seed": 2022,
      "edge_permutation": [
        6,
        4,
        0,
        3,
        7,
        5,
        2,
        1
      ],
      "repeat": 4,
      "target_accuracy": 32.8000009059906,
      "target_logprob_margin_mean": -3.3574302196502686,
      "target_logprob_margin_min": -13.815509796142578,
      "branch_active_tree_mi": 0.25275503773013436,
      "branch_active_root_mi": 0.11022207377847723,
      "tree_entropy_mean": 2.007650852203369,
      "root_entropy_mean": 0.5810825228691101,
      "active_tree_matched_comparison_gap_mean": -0.2947317287105671,
      "posterior_matched_comparison_gap_mean": -0.2289127386547002,
      "target_accuracy_delta": -52.399998903274536,
      "target_logprob_margin_mean_delta": -4.934475898742676,
      "target_logprob_margin_min_delta": -11.987230896949768,
      "branch_active_tree_mi_delta": -0.21914100690605737,
      "branch_active_root_mi_delta": -0.26321318935976157,
      "tree_entropy_mean_delta": -0.2978658676147461,
      "root_entropy_mean_delta": -0.19986122846603394,
      "active_tree_matched_comparison_gap_mean_delta": 0.14763374321850614,
      "posterior_matched_comparison_gap_mean_delta": 0.06841084058011543
    },
    {
      "intervention": "decoder_root_permutation",
      "seed": 3027,
      "root_permutation": [
        3,
        1,
        2,
        4,
        0
      ],
      "repeat": 0,
      "target_accuracy": 32.40000009536743,
      "target_logprob_margin_mean": -2.9294161796569824,
      "target_logprob_margin_min": -13.815510749816895,
      "branch_active_tree_mi": 0.4718960446361917,
      "branch_active_root_mi": 0.3734352631382388,
      "tree_entropy_mean": 2.3055167198181152,
      "root_entropy_mean": 0.780943751335144,
      "active_tree_matched_comparison_gap_mean": -0.4423654719290732,
      "posterior_matched_comparison_gap_mean": -0.2973235792348156,
      "target_accuracy_delta": -52.799999713897705,
      "target_logprob_margin_mean_delta": -4.50646185874939,
      "target_logprob_margin_min_delta": -11.987231850624084,
      "branch_active_tree_mi_delta": 0.0,
      "branch_active_root_mi_delta": 0.0,
      "tree_entropy_mean_delta": 0.0,
      "root_entropy_mean_delta": 0.0,
      "active_tree_matched_comparison_gap_mean_delta": 0.0,
      "posterior_matched_comparison_gap_mean_delta": 0.0
    },
    {
      "intervention": "decoder_root_permutation",
      "seed": 3028,
      "root_permutation": [
        4,
        2,
        0,
        3,
        1
      ],
      "repeat": 1,
      "target_accuracy": 43.799999356269836,
      "target_logprob_margin_mean": -1.7975225448608398,
      "target_logprob_margin_min": -13.815509796142578,
      "branch_active_tree_mi": 0.4718960446361917,
      "branch_active_root_mi": 0.3734352631382388,
      "tree_entropy_mean": 2.3055167198181152,
      "root_entropy_mean": 0.780943751335144,
      "active_tree_matched_comparison_gap_mean": -0.4423654719290732,
      "posterior_matched_comparison_gap_mean": -0.2973235792348156,
      "target_accuracy_delta": -41.4000004529953,
      "target_logprob_margin_mean_delta": -3.374568223953247,
      "target_logprob_margin_min_delta": -11.987230896949768,
      "branch_active_tree_mi_delta": 0.0,
      "branch_active_root_mi_delta": 0.0,
      "tree_entropy_mean_delta": 0.0,
      "root_entropy_mean_delta": 0.0,
      "active_tree_matched_comparison_gap_mean_delta": 0.0,
      "posterior_matched_comparison_gap_mean_delta": 0.0
    },
    {
      "intervention": "decoder_root_permutation",
      "seed": 3029,
      "root_permutation": [
        1,
        4,
        2,
        3,
        0
      ],
      "repeat": 2,
      "target_accuracy": 43.39999854564667,
      "target_logprob_margin_mean": -1.2456583976745605,
      "target_logprob_margin_min": -13.815510749816895,
      "branch_active_tree_mi": 0.4718960446361917,
      "branch_active_root_mi": 0.3734352631382388,
      "tree_entropy_mean": 2.3055167198181152,
      "root_entropy_mean": 0.780943751335144,
      "active_tree_matched_comparison_gap_mean": -0.4423654719290732,
      "posterior_matched_comparison_gap_mean": -0.2973235792348156,
      "target_accuracy_delta": -41.80000126361847,
      "target_logprob_margin_mean_delta": -2.8227040767669678,
      "target_logprob_margin_min_delta": -11.987231850624084,
      "branch_active_tree_mi_delta": 0.0,
      "branch_active_root_mi_delta": 0.0,
      "tree_entropy_mean_delta": 0.0,
      "root_entropy_mean_delta": 0.0,
      "active_tree_matched_comparison_gap_mean_delta": 0.0,
      "posterior_matched_comparison_gap_mean_delta": 0.0
    },
    {
      "intervention": "decoder_root_permutation",
      "seed": 3030,
      "root_permutation": [
        3,
        1,
        2,
        4,
        0
      ],
      "repeat": 3,
      "target_accuracy": 32.40000009536743,
      "target_logprob_margin_mean": -2.9294161796569824,
      "target_logprob_margin_min": -13.815510749816895,
      "branch_active_tree_mi": 0.4718960446361917,
      "branch_active_root_mi": 0.3734352631382388,
      "tree_entropy_mean": 2.3055167198181152,
      "root_entropy_mean": 0.780943751335144,
      "active_tree_matched_comparison_gap_mean": -0.4423654719290732,
      "posterior_matched_comparison_gap_mean": -0.2973235792348156,
      "target_accuracy_delta": -52.799999713897705,
      "target_logprob_margin_mean_delta": -4.50646185874939,
      "target_logprob_margin_min_delta": -11.987231850624084,
      "branch_active_tree_mi_delta": 0.0,
      "branch_active_root_mi_delta": 0.0,
      "tree_entropy_mean_delta": 0.0,
      "root_entropy_mean_delta": 0.0,
      "active_tree_matched_comparison_gap_mean_delta": 0.0,
      "posterior_matched_comparison_gap_mean_delta": 0.0
    },
    {
      "intervention": "decoder_root_permutation",
      "seed": 3031,
      "root_permutation": [
        0,
        3,
        1,
        2,
        4
      ],
      "repeat": 4,
      "target_accuracy": 26.199999451637268,
      "target_logprob_margin_mean": -3.6538751125335693,
      "target_logprob_margin_min": -13.780181884765625,
      "branch_active_tree_mi": 0.4718960446361917,
      "branch_active_root_mi": 0.3734352631382388,
      "tree_entropy_mean": 2.3055167198181152,
      "root_entropy_mean": 0.780943751335144,
      "active_tree_matched_comparison_gap_mean": -0.4423654719290732,
      "posterior_matched_comparison_gap_mean": -0.2973235792348156,
      "target_accuracy_delta": -59.00000035762787,
      "target_logprob_margin_mean_delta": -5.230920791625977,
      "target_logprob_margin_min_delta": -11.951902985572815,
      "branch_active_tree_mi_delta": 0.0,
      "branch_active_root_mi_delta": 0.0,
      "tree_entropy_mean_delta": 0.0,
      "root_entropy_mean_delta": 0.0,
      "active_tree_matched_comparison_gap_mean_delta": 0.0,
      "posterior_matched_comparison_gap_mean_delta": 0.0
    },
    {
      "intervention": "randomize_K_direction",
      "seed": 4036,
      "preserves_effective_row_norms": true,
      "preserves_input_mask": true,
      "repeat": 0,
      "target_accuracy": 35.600000619888306,
      "target_logprob_margin_mean": -3.087871551513672,
      "target_logprob_margin_min": -13.720344543457031,
      "branch_active_tree_mi": 0.05905028801606241,
      "branch_active_root_mi": 0.005231571150183512,
      "tree_entropy_mean": 1.9461325407028198,
      "root_entropy_mean": 0.6453959345817566,
      "active_tree_matched_comparison_gap_mean": -0.09426976054264324,
      "posterior_matched_comparison_gap_mean": -0.08623761197810678,
      "target_accuracy_delta": -49.59999918937683,
      "target_logprob_margin_mean_delta": -4.664917230606079,
      "target_logprob_margin_min_delta": -11.892065644264221,
      "branch_active_tree_mi_delta": -0.41284575662012934,
      "branch_active_root_mi_delta": -0.3682036919880553,
      "tree_entropy_mean_delta": -0.3593841791152954,
      "root_entropy_mean_delta": -0.13554781675338745,
      "active_tree_matched_comparison_gap_mean_delta": 0.34809571138643,
      "posterior_matched_comparison_gap_mean_delta": 0.21108596725670883
    },
    {
      "intervention": "randomize_K_direction",
      "seed": 4037,
      "preserves_effective_row_norms": true,
      "preserves_input_mask": true,
      "repeat": 1,
      "target_accuracy": 33.799999952316284,
      "target_logprob_margin_mean": -2.573587656021118,
      "target_logprob_margin_min": -13.662341117858887,
      "branch_active_tree_mi": 0.06805071038554891,
      "branch_active_root_mi": 0.03482726075913891,
      "tree_entropy_mean": 1.5626027584075928,
      "root_entropy_mean": 0.705872654914856,
      "active_tree_matched_comparison_gap_mean": -0.10417667025534492,
      "posterior_matched_comparison_gap_mean": -0.07541646355558407,
      "target_accuracy_delta": -51.39999985694885,
      "target_logprob_margin_mean_delta": -4.150633335113525,
      "target_logprob_margin_min_delta": -11.834062218666077,
      "branch_active_tree_mi_delta": -0.40384533425064284,
      "branch_active_root_mi_delta": -0.33860800237909994,
      "tree_entropy_mean_delta": -0.7429139614105225,
      "root_entropy_mean_delta": -0.07507109642028809,
      "active_tree_matched_comparison_gap_mean_delta": 0.3381888016737283,
      "posterior_matched_comparison_gap_mean_delta": 0.22190711567923155
    },
    {
      "intervention": "randomize_K_direction",
      "seed": 4038,
      "preserves_effective_row_norms": true,
      "preserves_input_mask": true,
      "repeat": 2,
      "target_accuracy": 28.00000011920929,
      "target_logprob_margin_mean": -3.3977456092834473,
      "target_logprob_margin_min": -13.70032024383545,
      "branch_active_tree_mi": 0.10394300823211382,
      "branch_active_root_mi": 0.04186535678002649,
      "tree_entropy_mean": 1.611588954925537,
      "root_entropy_mean": 0.7838972210884094,
      "active_tree_matched_comparison_gap_mean": -0.15056007345602582,
      "posterior_matched_comparison_gap_mean": -0.13515370761852252,
      "target_accuracy_delta": -57.19999969005585,
      "target_logprob_margin_mean_delta": -4.9747912883758545,
      "target_logprob_margin_min_delta": -11.87204134464264,
      "branch_active_tree_mi_delta": -0.3679530364040779,
      "branch_active_root_mi_delta": -0.3315699063582123,
      "tree_entropy_mean_delta": -0.6939277648925781,
      "root_entropy_mean_delta": 0.002953469753265381,
      "active_tree_matched_comparison_gap_mean_delta": 0.29180539847304743,
      "posterior_matched_comparison_gap_mean_delta": 0.1621698716162931
    },
    {
      "intervention": "randomize_K_direction",
      "seed": 4039,
      "preserves_effective_row_norms": true,
      "preserves_input_mask": true,
      "repeat": 3,
      "target_accuracy": 27.59999930858612,
      "target_logprob_margin_mean": -4.264723300933838,
      "target_logprob_margin_min": -13.774972915649414,
      "branch_active_tree_mi": 0.08222870134208207,
      "branch_active_root_mi": 0.016281195502612943,
      "tree_entropy_mean": 1.6825590133666992,
      "root_entropy_mean": 0.6626014113426208,
      "active_tree_matched_comparison_gap_mean": -0.0626052992802995,
      "posterior_matched_comparison_gap_mean": -0.05460410695534084,
      "target_accuracy_delta": -57.600000500679016,
      "target_logprob_margin_mean_delta": -5.841768980026245,
      "target_logprob_margin_min_delta": -11.946694016456604,
      "branch_active_tree_mi_delta": -0.3896673432941097,
      "branch_active_root_mi_delta": -0.3571540676356259,
      "tree_entropy_mean_delta": -0.622957706451416,
      "root_entropy_mean_delta": -0.1183423399925232,
      "active_tree_matched_comparison_gap_mean_delta": 0.3797601726487737,
      "posterior_matched_comparison_gap_mean_delta": 0.24271947227947477
    },
    {
      "intervention": "randomize_K_direction",
      "seed": 4040,
      "preserves_effective_row_norms": true,
      "preserves_input_mask": true,
      "repeat": 4,
      "target_accuracy": 35.40000021457672,
      "target_logprob_margin_mean": -3.1178507804870605,
      "target_logprob_margin_min": -13.784692764282227,
      "branch_active_tree_mi": 0.0915798981814721,
      "branch_active_root_mi": 0.01232092515266794,
      "tree_entropy_mean": 1.9573824405670166,
      "root_entropy_mean": 0.6578167676925659,
      "active_tree_matched_comparison_gap_mean": -0.09135710025926862,
      "posterior_matched_comparison_gap_mean": -0.07352544065260487,
      "target_accuracy_delta": -49.799999594688416,
      "target_logprob_margin_mean_delta": -4.694896459579468,
      "target_logprob_margin_min_delta": -11.956413865089417,
      "branch_active_tree_mi_delta": -0.3803161464547196,
      "branch_active_root_mi_delta": -0.3611143379855709,
      "tree_entropy_mean_delta": -0.34813427925109863,
      "root_entropy_mean_delta": -0.12312698364257812,
      "active_tree_matched_comparison_gap_mean_delta": 0.3510083716698046,
      "posterior_matched_comparison_gap_mean_delta": 0.22379813858221076
    }
  ]
}